rain_table/__init__.py
rain_table/_version.py
rain_table/events.py
rain_table/rain_table.py
rain_table/slider_manager.py
rain_table/utils.py
rain_table/widgets.py
rain_table-3.0.4.dist-info/METADATA
rain_table-3.0.4.dist-info/RECORD
rain_table-3.0.4.dist-info/WHEEL
rain_table-3.0.4.dist-info/top_level.txt
