Metadata-Version: 2.1
Name: rain-table
Version: 3.0.4
Summary: educational activity for teaching how water is routed through a drainage basin
Home-page: https://github.com/sededu/rain_table
Author: Jeffrey Kwang and Andrew J. Moodie
Author-email: amoodie@rice.edu
License: LICENSE.txt
Project-URL: Source, https://github.com/sededu/rain_table
Project-URL: Bug Reports, https://github.com/sededu/rain_table/issues
Platform: UNKNOWN
Classifier: Development Status :: 4 - Beta
Classifier: License :: OSI Approved :: MIT License
Classifier: Intended Audience :: Education
Classifier: Intended Audience :: End Users/Desktop
Classifier: Intended Audience :: Science/Research
Classifier: Topic :: Education
Requires-Python: >=3
Requires-Dist: scipy
Requires-Dist: numpy
Requires-Dist: matplotlib
Requires-Dist: shapely
Requires-Dist: pillow
